pretab/__init__.py
pretab/__version__.py
pretab/preprocessor.py
pretab/transformers/__init__.py
pretab/transformers/binning/__init__.py
pretab/transformers/binning/binning.py
pretab/transformers/embeddings/__init__.py
pretab/transformers/embeddings/language_transformer.py
pretab/transformers/feature_maps/__init__.py
pretab/transformers/feature_maps/rbf.py
pretab/transformers/feature_maps/relu.py
pretab/transformers/feature_maps/sigmoid.py
pretab/transformers/feature_maps/tanh.py
pretab/transformers/onehot/__init__.py
pretab/transformers/onehot/onehot.py
pretab/transformers/ple/__init__.py
pretab/transformers/ple/ple.py
pretab/transformers/ple/tree_to_code.py
pretab/transformers/splines/__init__.py
pretab/transformers/splines/cubic.py
pretab/transformers/splines/integrated_spline.py
pretab/transformers/splines/natural_cubic.py
pretab/transformers/splines/p_spline.py
pretab/transformers/splines/tensor_product.py
pretab/transformers/splines/thinplate_spline.py
pretab/transformers/temporal/__init__.py
pretab/transformers/temporal/cyclic.py
pretab/transformers/temporal/lag.py
pretab/transformers/temporal/rolling_stats.py
pretab/transformers/utils/__init__.py
pretab/transformers/utils/continuous_ordinal.py
pretab/transformers/utils/floats.py
pretab/transformers/utils/utils.py
pretab/utils/__init__.py
pretab/utils/get_categorical.py
pretab/utils/get_numerical.py
pretab-0.0.3.dist-info/LICENSE
pretab-0.0.3.dist-info/METADATA
pretab-0.0.3.dist-info/WHEEL
pretab-0.0.3.dist-info/top_level.txt
pretab-0.0.3.dist-info/RECORD
