Metadata-Version: 2.1
Name: pretab
Version: 0.0.3
Summary: A python package for preprocessing tabular data
Home-page: https://github.com/OpenTabular/PreTab
Author: Anton Thielmann
Author-email: antonthielmann@t-online.de.de
License: MIT
Platform: UNKNOWN
Classifier: Programming Language :: Python :: 3
Classifier: License :: OSI Approved :: MIT License
Classifier: Operating System :: OS Independent
Requires-Python: >=3.6
Requires-Dist: numpy
Requires-Dist: scikit-learn
Requires-Dist: scipy
Requires-Dist: pandas
